README.txt
setup.py
cntalib/__init__.py
cntalib.egg-info/PKG-INFO
cntalib.egg-info/SOURCES.txt
cntalib.egg-info/dependency_links.txt
cntalib.egg-info/not-zip-safe
cntalib.egg-info/requires.txt
cntalib.egg-info/top_level.txt
cntalib/K_matching/K_matching.py
cntalib/K_matching/__init__.py
cntalib/Logic/Logic.py
cntalib/Logic/__init__.py
cntalib/Reference/Reference.py
cntalib/Reference/__init__.py