Metadata-Version: 1.0
Name: cntalib
Version: 20170310
Summary: China stock market technical analysis library
Home-page: https://github.com
Author: Jian Xue
Author-email: cntalib@qq.com
License: GNU
Keywords: China stock market technical analysis library
Platform: UNKNOWN
